zhouxiaotao_mcp_demo/__init__.py
zhouxiaotao_mcp_demo-0.1.0.dist-info/METADATA
zhouxiaotao_mcp_demo-0.1.0.dist-info/WHEEL
zhouxiaotao_mcp_demo-0.1.0.dist-info/entry_points.txt
zhouxiaotao_mcp_demo-0.1.0.dist-info/RECORD
