Metadata-Version: 2.4
Name: zhouxiaotao-mcp-demo
Version: 0.1.0
Summary: Add your description here
Author-email: zhoutaohui <zhoutaohui@apiire.com>
Requires-Python: >=3.13
Requires-Dist: mcp[cli]>=1.9.3
